[
  {
   "id": "120363423627310679@newsletter",
    "desc": "SanzzCyt #1"
  },
  {
    "id": "120363428261257878@newsletter",
    "desc": "SsnzzCYt #2"
  },
  {
    "id": "id",
    "desc": "nama"
  },
  {
   "id": "id",
    "desc": "nama"
  },
  {
    "id": "id",
    "desc": "nama"
  },
  {
    "id": "id",
    "desc": "nama"
  },
  {
    "id": "id",
    "desc": "nama"
  },
  {
   "id": "id",
    "desc": "nama"
  },
  {
    "id": "id",
    "desc": "nama"
  },
  {
    "id": "id",
    "desc": "nama"
  },
  {
    "id": "id",
    "desc": "nama"
  },
  {
   "id": "id",
    "desc": "nama"
  }
]
